{
  "type": "FeatureCollection",
  "features": [
    {
      "type": "Feature",
      "properties": {
        "name": "Koli National Park",
        "country": "Finland",
        "countryCode": "FI",
        "category": "viewpoint",
        "rating": 4,
        "description": "Finland's most famous view from Ukko-Koli Hill over Lake Pielinen"
      },
      "geometry": { "type": "Point", "coordinates": [29.8000, 63.0833] }
    },
    {
      "type": "Feature",
      "properties": {
        "name": "Suomenlinna Sea Fortress",
        "country": "Finland",
        "countryCode": "FI",
        "category": "landmark",
        "rating": 3,
        "description": "UNESCO island fortress spreading across six islands"
      },
      "geometry": { "type": "Point", "coordinates": [24.9833, 60.1453] }
    }
  ]
}
