{
  "type": "FeatureCollection",
  "features": [
    {
      "type": "Feature",
      "properties": {
        "name": "Ruta de las Flores",
        "country": "El Salvador",
        "countryCode": "SV",
        "category": "viewpoint",
        "rating": 3,
        "description": "Scenic mountain route through coffee plantations and colorful colonial villages"
      },
      "geometry": { "type": "Point", "coordinates": [-89.7833, 13.8500] }
    },
    {
      "type": "Feature",
      "properties": {
        "name": "Joya de Ceren",
        "country": "El Salvador",
        "countryCode": "SV",
        "category": "landmark",
        "rating": 3,
        "description": "Pompeii of the Americas - UNESCO ancient village preserved by volcanic ash"
      },
      "geometry": { "type": "Point", "coordinates": [-89.3522, 13.8319] }
    }
  ]
}
