{
  "type": "FeatureCollection",
  "features": [
    {
      "type": "Feature",
      "properties": {
        "name": "Bwindi Impenetrable Forest",
        "country": "Uganda",
        "countryCode": "UG",
        "category": "natural",
        "rating": 5,
        "description": "UNESCO site home to half the world's mountain gorilla population"
      },
      "geometry": { "type": "Point", "coordinates": [29.6500, -1.0500] }
    },
    {
      "type": "Feature",
      "properties": {
        "name": "Murchison Falls",
        "country": "Uganda",
        "countryCode": "UG",
        "category": "natural",
        "rating": 4,
        "description": "Nile forces through 7m gap creating the world's most powerful waterfall by force"
      },
      "geometry": { "type": "Point", "coordinates": [31.6833, 2.2833] }
    }
  ]
}
