{
  "type": "FeatureCollection",
  "features": [
    {
      "type": "Feature",
      "geometry": { "type": "Point", "coordinates": [17.8078, 43.3438] },
      "properties": { "name": "Mostar", "country": "Bosnia", "iso": "BA", "source": "Route", "category": "Stop", "trip": 15, "nights": "" }
    },
    {
      "type": "Feature",
      "geometry": { "type": "Point", "coordinates": [18.4131, 43.8563] },
      "properties": { "name": "Sarajevo", "country": "Bosnia", "iso": "BA", "source": "Route", "category": "Stop", "trip": 15, "nights": "" }
    },
    {
      "type": "Feature",
      "geometry": { "type": "Point", "coordinates": [17.815, 43.3373] },
      "properties": { "name": "Stari Most (Old Bridge of Mostar)", "country": "Bosnia", "iso": "BA", "source": "Sight", "category": "Cultural", "score": 9, "why_notable": "Iconic 16th-century Ottoman bridge, symbol of reconciliation, UNESCO" }
    },
    {
      "type": "Feature",
      "geometry": { "type": "Point", "coordinates": [18.431, 43.859] },
      "properties": { "name": "Ćevabdžinica Željo", "city": "Sarajevo", "country": "Bosnia", "iso": "BA", "source": "LocalEatery", "category": "Restaurant", "why_notable": "Best ćevapi in Bosnia" }
    }
  ]
}
