{
  "type": "FeatureCollection",
  "features": [
    {
      "type": "Feature",
      "geometry": {
        "type": "Point",
        "coordinates": [
          16.55416667,
          2.609444444
        ]
      },
      "properties": {
        "name": "Sangha Trinational",
        "country": "Cameroon,Central African Republic,Congo",
        "iso": "CF",
        "source": "UNESCO",
        "category": "N",
        "year_inscribed": "2012",
        "danger": false
      }
    }
  ]
}