{
  "type": "FeatureCollection",
  "features": [
    {
      "type": "Feature",
      "geometry": {
        "type": "Point",
        "coordinates": [
          15.2663,
          -4.2634
        ]
      },
      "properties": {
        "name": "Brazzaville",
        "country": "Congo",
        "iso": "CG",
        "source": "Route",
        "category": "Stop",
        "trip": 19,
        "nights": ""
      }
    },
    {
      "type": "Feature",
      "geometry": {
        "type": "Point",
        "coordinates": [
          15.2663,
          -4.2634
        ]
      },
      "properties": {
        "name": "Brazzaville",
        "country": "Congo",
        "iso": "CG",
        "source": "Suggestion",
        "category": "City",
        "why_notable": "Capital facing Kinshasa across Congo River, Basilique Sainte-Anne"
      }
    },
    {
      "type": "Feature",
      "geometry": {
        "type": "Point",
        "coordinates": [
          14.85,
          1.25
        ]
      },
      "properties": {
        "name": "Odzala-Kokoua National Park",
        "country": "Congo",
        "iso": "CG",
        "source": "Suggestion",
        "category": "Natural",
        "why_notable": "One of Africa's oldest parks, lowland gorillas, forest elephants"
      }
    },
    {
      "type": "Feature",
      "geometry": {
        "type": "Point",
        "coordinates": [
          11.8636,
          -4.7761
        ]
      },
      "properties": {
        "name": "Pointe-Noire",
        "country": "Congo",
        "iso": "CG",
        "source": "Suggestion",
        "category": "City",
        "why_notable": "Atlantic port city, beaches, Gorges de Diosso (red canyons)"
      }
    },
    {
      "type": "Feature",
      "geometry": {
        "type": "Point",
        "coordinates": [
          15.05,
          -4.17
        ]
      },
      "properties": {
        "name": "Les Rapides",
        "country": "Congo",
        "iso": "CG",
        "source": "Suggestion",
        "category": "Natural",
        "why_notable": "Congo River rapids, popular weekend spot, local fish restaurants"
      }
    }
  ]
}