{
  "type": "FeatureCollection",
  "features": [
    {
      "type": "Feature",
      "geometry": { "type": "Point", "coordinates": [44.8271, 41.7151] },
      "properties": { "name": "Tbilisi", "country": "Georgia", "iso": "GE", "source": "Route", "category": "Stop", "trip": 16, "nights": "" }
    },
    {
      "type": "Feature",
      "geometry": { "type": "Point", "coordinates": [44.6199, 42.6614] },
      "properties": { "name": "Kazbegi", "country": "Georgia", "iso": "GE", "source": "Route", "category": "Stop", "trip": 16, "nights": "" }
    },
    {
      "type": "Feature",
      "geometry": { "type": "Point", "coordinates": [44.6199, 42.6614] },
      "properties": { "name": "Gergeti Trinity Church", "country": "Georgia", "iso": "GE", "source": "Sight", "category": "Cultural", "score": 8, "why_notable": "Iconic 14th-century church beneath Mount Kazbek, Georgia's most photographed landmark" }
    },
    {
      "type": "Feature",
      "geometry": { "type": "Point", "coordinates": [43.01139, 42.91639] },
      "properties": { "name": "Upper Svaneti", "country": "Georgia", "iso": "GE", "source": "Sight", "category": "Cultural", "score": 8, "why_notable": "Remote medieval towers in Caucasus, UNESCO, preserved mountain culture" }
    },
    {
      "type": "Feature",
      "geometry": { "type": "Point", "coordinates": [44.72103, 41.84228] },
      "properties": { "name": "Mtskheta", "country": "Georgia", "iso": "GE", "source": "Sight", "category": "Cultural", "score": 8, "why_notable": "Ancient capital, early Christian sites, Jvari Monastery, UNESCO" }
    }
  ]
}
