{
  "type": "FeatureCollection",
  "features": [
    {
      "type": "Feature",
      "geometry": {
        "type": "Point",
        "coordinates": [
          41.9512,
          41.70227778
        ]
      },
      "properties": {
        "name": "Colchic Rainforests and Wetlands",
        "country": "Georgia",
        "iso": "GE",
        "source": "UNESCO",
        "category": "N",
        "year_inscribed": "2021",
        "danger": false
      }
    },
    {
      "type": "Feature",
      "geometry": {
        "type": "Point",
        "coordinates": [
          42.76833333,
          42.29472222
        ]
      },
      "properties": {
        "name": "Gelati Monastery",
        "country": "Georgia",
        "iso": "GE",
        "source": "UNESCO",
        "category": "C",
        "year_inscribed": "1994",
        "danger": false
      }
    },
    {
      "type": "Feature",
      "geometry": {
        "type": "Point",
        "coordinates": [
          44.72102778,
          41.84227778
        ]
      },
      "properties": {
        "name": "Historical Monuments of Mtskheta",
        "country": "Georgia",
        "iso": "GE",
        "source": "UNESCO",
        "category": "C",
        "year_inscribed": "1994",
        "danger": false
      }
    },
    {
      "type": "Feature",
      "geometry": {
        "type": "Point",
        "coordinates": [
          43.01139,
          42.91639
        ]
      },
      "properties": {
        "name": "Upper Svaneti",
        "country": "Georgia",
        "iso": "GE",
        "source": "UNESCO",
        "category": "C",
        "year_inscribed": "1996",
        "danger": false
      }
    },
    {
      "type": "Feature",
      "geometry": null,
      "properties": {
        "name": "Old Tbilisi",
        "country": "Georgia",
        "iso": "GE",
        "source": "LP500",
        "category": "Destination"
      }
    },
    {
      "type": "Feature",
      "geometry": null,
      "properties": {
        "name": "David Gareja Monastery",
        "country": "Georgia",
        "iso": "GE",
        "source": "LP500",
        "category": "Destination"
      }
    }
  ]
}