{
  "type": "FeatureCollection",
  "features": [
    {
      "type": "Feature",
      "geometry": { "type": "Point", "coordinates": [18.7712, 42.4247] },
      "properties": { "name": "Kotor", "country": "Montenegro", "iso": "ME", "source": "Route", "category": "Stop", "trip": 15, "nights": "" }
    },
    {
      "type": "Feature",
      "geometry": { "type": "Point", "coordinates": [19.2636, 42.4304] },
      "properties": { "name": "Podgorica", "country": "Montenegro", "iso": "ME", "source": "Route", "category": "Stop", "trip": 15, "nights": "" }
    },
    {
      "type": "Feature",
      "geometry": { "type": "Point", "coordinates": [18.7, 42.4833] },
      "properties": { "name": "Bay of Kotor", "country": "Montenegro", "iso": "ME", "source": "Sight", "category": "Natural", "score": 9, "why_notable": "Europe's southernmost fjord, medieval walled town, stunning scenery, UNESCO" }
    },
    {
      "type": "Feature",
      "geometry": { "type": "Point", "coordinates": [19.0303, 42.6767] },
      "properties": { "name": "Ostrog Monastery", "country": "Montenegro", "iso": "ME", "source": "Sight", "category": "Cultural", "score": 8, "why_notable": "Cliff-face Serbian Orthodox monastery, pilgrimage site" }
    },
    {
      "type": "Feature",
      "geometry": { "type": "Point", "coordinates": [19.0166, 43.133] },
      "properties": { "name": "Durmitor National Park", "country": "Montenegro", "iso": "ME", "source": "Sight", "category": "Natural", "score": 8, "why_notable": "Dramatic mountain landscapes, Tara Canyon, glacial lakes, UNESCO" }
    }
  ]
}
