{
  "type": "FeatureCollection",
  "features": [
    {
      "type": "Feature",
      "geometry": {
        "type": "Point",
        "coordinates": [
          32.5892,
          -25.9692
        ]
      },
      "properties": {
        "name": "Maputo",
        "country": "Mozambique",
        "iso": "MZ",
        "source": "Route",
        "category": "Stop",
        "trip": 20,
        "nights": ""
      }
    },
    {
      "type": "Feature",
      "geometry": {
        "type": "Point",
        "coordinates": [
          40.7358,
          -15.0342
        ]
      },
      "properties": {
        "name": "Island of Mozambique",
        "country": "Mozambique",
        "iso": "MZ",
        "source": "Sight",
        "category": "Cultural",
        "score": 8,
        "why_notable": "Portuguese colonial architecture, historic trading post, UNESCO"
      }
    }
  ]
}
