{
  "type": "FeatureCollection",
  "features": [
    {
      "type": "Feature",
      "geometry": { "type": "Point", "coordinates": [58.4059, 23.588] },
      "properties": { "name": "Muscat", "country": "Oman", "iso": "OM", "source": "Route", "category": "Stop", "trip": 1, "nights": "" }
    },
    {
      "type": "Feature",
      "geometry": { "type": "Point", "coordinates": [57.5311, 22.9333] },
      "properties": { "name": "Nizwa", "country": "Oman", "iso": "OM", "source": "Route", "category": "Stop", "trip": 1, "nights": "" }
    },
    {
      "type": "Feature",
      "geometry": { "type": "Point", "coordinates": [57.5, 23.0] },
      "properties": { "name": "Nizwa & Interior Forts", "country": "Oman", "iso": "OM", "source": "Sight", "category": "Cultural", "score": 8, "why_notable": "Ancient forts, souqs, authentic Arabia, Bahla Fort UNESCO" }
    }
  ]
}
