{
  "type": "FeatureCollection",
  "features": [
    {
      "type": "Feature",
      "properties": {
        "name": "Cape Coast Castle",
        "country": "Ghana",
        "countryCode": "GH",
        "category": "landmark",
        "rating": 4,
        "description": "UNESCO slave castle, powerful memorial to the transatlantic slave trade"
      },
      "geometry": { "type": "Point", "coordinates": [-1.2431, 5.1058] }
    },
    {
      "type": "Feature",
      "properties": {
        "name": "Kakum National Park Canopy Walk",
        "country": "Ghana",
        "countryCode": "GH",
        "category": "natural",
        "rating": 3,
        "description": "350m walkway 40m above rainforest floor in pristine tropical forest"
      },
      "geometry": { "type": "Point", "coordinates": [-1.3833, 5.3500] }
    }
  ]
}
