{
  "type": "FeatureCollection",
  "features": [
    {
      "type": "Feature",
      "properties": {
        "name": "Jesuit Missions of Trinidad and Jesus",
        "country": "Paraguay",
        "countryCode": "PY",
        "category": "landmark",
        "rating": 3,
        "description": "UNESCO ruins of 17th-century Jesuit missions in their best-preserved state"
      },
      "geometry": { "type": "Point", "coordinates": [-55.7206, -27.1314] }
    },
    {
      "type": "Feature",
      "properties": {
        "name": "Monday Falls",
        "country": "Paraguay",
        "countryCode": "PY",
        "category": "natural",
        "rating": 3,
        "description": "145-foot waterfall near Iguazu, often crowd-free alternative"
      },
      "geometry": { "type": "Point", "coordinates": [-54.5978, -25.5222] }
    },
    {
      "type": "Feature",
      "properties": {
        "name": "Itaipu Dam",
        "country": "Paraguay",
        "countryCode": "PY",
        "category": "landmark",
        "rating": 2,
        "description": "One of world's largest hydroelectric dams on Paraguay-Brazil border"
      },
      "geometry": { "type": "Point", "coordinates": [-54.5917, -25.4083] }
    }
  ]
}
